kisters/network_store/service/padp/asgi/__init__.py
kisters/network_store/service/padp/asgi/app.py
kisters/network_store/service/padp/asgi/settings.py
kisters/network_store/service/padp/asgi/routers/__init__.py
kisters/network_store/service/padp/asgi/routers/networks.py
kisters/network_store/service/padp/asgi/routers/schemas.py
kisters/network_store/service/padp/asgi/routers/viewer.py
kisters/network_store/service/padp/asgi/static/Channel.svg
kisters/network_store/service/padp/asgi/static/Delay.svg
kisters/network_store/service/padp/asgi/static/Drain.svg
kisters/network_store/service/padp/asgi/static/FlowBoundary.svg
kisters/network_store/service/padp/asgi/static/FlowControlledStructure.svg
kisters/network_store/service/padp/asgi/static/Gate.svg
kisters/network_store/service/padp/asgi/static/GeneratingStation.svg
kisters/network_store/service/padp/asgi/static/Junction-hidden.svg
kisters/network_store/service/padp/asgi/static/Junction.svg
kisters/network_store/service/padp/asgi/static/LevelBoundary.svg
kisters/network_store/service/padp/asgi/static/Pipe.svg
kisters/network_store/service/padp/asgi/static/Pump.svg
kisters/network_store/service/padp/asgi/static/RectangularOrifice.svg
kisters/network_store/service/padp/asgi/static/Reservoir.svg
kisters/network_store/service/padp/asgi/static/SphericalOrifice.svg
kisters/network_store/service/padp/asgi/static/Storage.svg
kisters/network_store/service/padp/asgi/static/Subsystem.svg
kisters/network_store/service/padp/asgi/static/Tank.svg
kisters/network_store/service/padp/asgi/static/Turbine.svg
kisters/network_store/service/padp/asgi/static/Unknown.svg
kisters/network_store/service/padp/asgi/static/Valve.svg
kisters/network_store/service/padp/asgi/static/Waterfall.svg
kisters/network_store/service/padp/asgi/static/Weir.svg
kisters/network_store/service/padp/asgi/static/swagger-ui-bundle.js
kisters/network_store/service/padp/asgi/static/swagger-ui-bundle.js.map
kisters/network_store/service/padp/asgi/static/swagger-ui.css
kisters.network_store.service-1.4.0.dist-info/METADATA
kisters.network_store.service-1.4.0.dist-info/WHEEL
kisters.network_store.service-1.4.0.dist-info/top_level.txt
kisters.network_store.service-1.4.0.dist-info/RECORD
