Metadata-Version: 2.1
Name: kisters.network-store.service
Version: 1.4.0
Summary: Storage, Retrieval, and Versioning of Infrastructure Networks
Home-page: https://gitlab.com/kisters/network-store/service
Author: Jesse VanderWees
Author-email: jesse.vanderwees@kisters-bv.nl
License: UNKNOWN
Keywords: hydraulics infrastructure graph topology
Platform: UNKNOWN
Classifier: Development Status :: 3 - Alpha
Classifier: Programming Language :: Python :: 3.9
Classifier: Programming Language :: Python :: 3.10
Classifier: Programming Language :: Python :: 3.11
Requires-Dist: bokeh
Requires-Dist: fastapi
Requires-Dist: kisters.network-store.model-library (>=0.2.9)
Requires-Dist: motor
Requires-Dist: numpy
Requires-Dist: orjson
Requires-Dist: pydantic[dotenv]
Requires-Dist: pymongo
Requires-Dist: scipy
Requires-Dist: starlette
Provides-Extra: test
Requires-Dist: pytest ; extra == 'test'
Requires-Dist: pytest-cov ; extra == 'test'
Requires-Dist: pytest-asyncio ; extra == 'test'
Requires-Dist: kisters.network-store.model-library.water (>=0.2.13) ; extra == 'test'
Requires-Dist: httpx ; extra == 'test'
